emanifest/__init__.py
emanifest/client.py
emanifest/py.typed
emanifest/types.py
emanifest-5.1.0.dist-info/licenses/LICENSE.txt
emanifest-5.1.0.dist-info/METADATA
emanifest-5.1.0.dist-info/WHEEL
emanifest-5.1.0.dist-info/top_level.txt
emanifest-5.1.0.dist-info/RECORD
