Metadata-Version: 2.4
Name: emanifest
Version: 5.1.0
Summary: An API utility wrapper for accessing the e-Manifest hazardous waste tracking system maintained by the US Environmental Protection Agency
Author-email: William Nicholas  <nicholas.william@epa.gov>
Maintainer-email: William Nicholas <nicholas.william@epa.gov>, Scott Christian <christian.scott@epa.gov>
License: CCO 1.0
Project-URL: issues, https://github.com/USEPA/e-Manifest/issues
Project-URL: documentation, https://github.com/USEPA/e-Manifest/emanifest-py
Project-URL: homepage, https://github.com/USEPA/e-Manifest
Project-URL: repository, https://github.com/USEPA/e-Manifest
Requires-Python: >=3.10
License-File: LICENSE.txt
Requires-Dist: requests<3.0.0,>=2.0.0
Requires-Dist: requests-toolbelt<=1.0.0
Dynamic: license-file
